<?xml version="1.0" encoding="UTF-8"?>
<!DOCTYPE mapper PUBLIC "-//mybatis.org//DTD Mapper 3.0//EN" "http://mybatis.org/dtd/mybatis-3-mapper.dtd">
<mapper namespace="com.ariix.twInvoice.PromotionTypeMapper">
  <resultMap id="BaseResultMap" type="com.ariix.twInvoice.PromotionType">
    <!--
      WARNING - @mbggenerated
      This element is automatically generated by MyBatis Generator, do not modify.
      This element was generated on Mon Jan 22 16:22:52 CST 2018.
    -->
    <id column="ID" jdbcType="DECIMAL" property="id" />
    <result column="NAME" jdbcType="VARCHAR" property="name" />
    <result column="DESCRIPTION" jdbcType="VARCHAR" property="description" />
  </resultMap>
  <sql id="Base_Column_List">
    <!--
      WARNING - @mbggenerated
      This element is automatically generated by MyBatis Generator, do not modify.
      This element was generated on Mon Jan 22 16:22:52 CST 2018.
    -->
    ID, NAME, DESCRIPTION
  </sql>
  <select id="selectByPrimaryKey" parameterType="java.lang.Long" resultMap="BaseResultMap">
    <!--
      WARNING - @mbggenerated
      This element is automatically generated by MyBatis Generator, do not modify.
      This element was generated on Mon Jan 22 16:22:52 CST 2018.
    -->
    select 
    <include refid="Base_Column_List" />
    from PROMOTION_TYPE
    where ID = #{id,jdbcType=DECIMAL}
  </select>
  <delete id="deleteByPrimaryKey" parameterType="java.lang.Long">
    <!--
      WARNING - @mbggenerated
      This element is automatically generated by MyBatis Generator, do not modify.
      This element was generated on Mon Jan 22 16:22:52 CST 2018.
    -->
    delete from PROMOTION_TYPE
    where ID = #{id,jdbcType=DECIMAL}
  </delete>
  <insert id="insert" parameterType="com.ariix.twInvoice.PromotionType">
    <!--
      WARNING - @mbggenerated
      This element is automatically generated by MyBatis Generator, do not modify.
      This element was generated on Mon Jan 22 16:22:52 CST 2018.
    -->
    insert into PROMOTION_TYPE (ID, NAME, DESCRIPTION
      )
    values (#{id,jdbcType=DECIMAL}, #{name,jdbcType=VARCHAR}, #{description,jdbcType=VARCHAR}
      )
  </insert>
  <insert id="insertSelective" parameterType="com.ariix.twInvoice.PromotionType">
    <!--
      WARNING - @mbggenerated
      This element is automatically generated by MyBatis Generator, do not modify.
      This element was generated on Mon Jan 22 16:22:52 CST 2018.
    -->
    insert into PROMOTION_TYPE
    <trim prefix="(" suffix=")" suffixOverrides=",">
      <if test="id != null">
        ID,
      </if>
      <if test="name != null">
        NAME,
      </if>
      <if test="description != null">
        DESCRIPTION,
      </if>
    </trim>
    <trim prefix="values (" suffix=")" suffixOverrides=",">
      <if test="id != null">
        #{id,jdbcType=DECIMAL},
      </if>
      <if test="name != null">
        #{name,jdbcType=VARCHAR},
      </if>
      <if test="description != null">
        #{description,jdbcType=VARCHAR},
      </if>
    </trim>
  </insert>
  <update id="updateByPrimaryKeySelective" parameterType="com.ariix.twInvoice.PromotionType">
    <!--
      WARNING - @mbggenerated
      This element is automatically generated by MyBatis Generator, do not modify.
      This element was generated on Mon Jan 22 16:22:52 CST 2018.
    -->
    update PROMOTION_TYPE
    <set>
      <if test="name != null">
        NAME = #{name,jdbcType=VARCHAR},
      </if>
      <if test="description != null">
        DESCRIPTION = #{description,jdbcType=VARCHAR},
      </if>
    </set>
    where ID = #{id,jdbcType=DECIMAL}
  </update>
  <update id="updateByPrimaryKey" parameterType="com.ariix.twInvoice.PromotionType">
    <!--
      WARNING - @mbggenerated
      This element is automatically generated by MyBatis Generator, do not modify.
      This element was generated on Mon Jan 22 16:22:52 CST 2018.
    -->
    update PROMOTION_TYPE
    set NAME = #{name,jdbcType=VARCHAR},
      DESCRIPTION = #{description,jdbcType=VARCHAR}
    where ID = #{id,jdbcType=DECIMAL}
  </update>
</mapper>